README.md
setup.cfg
setup.py
hyperscalar/__init__.py
hyperscalar.egg-info/PKG-INFO
hyperscalar.egg-info/SOURCES.txt
hyperscalar.egg-info/dependency_links.txt
hyperscalar.egg-info/top_level.txt