Metadata-Version: 1.2
Name: hyperscalar
Version: 0.0.1
Summary: Next generation type
Home-page: https://github.com/fpgaco/hyperscalar
Author: Kenso Trabing
Author-email: ktrabing@acm.org
Maintainer: Kenso Trabing
Maintainer-email: ktrabing@acm.org
License:                                  Apache License
